__main__.py
qta-manage.py
qtaf_settings.py
qta_statics/TestReport.xsl
qta_statics/TestResult.xsl
qta_statics/__init__.py
qta_statics/qta-report.html
qtaf-5.6.11.dist-info/licenses/LICENSE.TXT
testbase/__init__.py
testbase/assertion.py
testbase/conf.py
testbase/context.py
testbase/datadrive.py
testbase/dist.py
testbase/exlib.py
testbase/loader.py
testbase/logger.py
testbase/management.py
testbase/plan.py
testbase/project.py
testbase/report.py
testbase/resource.py
testbase/retry.py
testbase/runner.py
testbase/serialization.py
testbase/test.py
testbase/testcase.py
testbase/testresult.py
testbase/testsuite.py
testbase/types.py
testbase/util.py
testbase/version.py
testbase/compat/__init__.py
testbase/compat/_imp.py
tuia/__init__.py
tuia/_tif.py
tuia/accessible.py
tuia/app.py
tuia/control.py
tuia/env.py
tuia/exceptions.py
tuia/filedialog.py
tuia/gfcontrols.py
tuia/keyboard.py
tuia/mouse.py
tuia/qpath.py
tuia/qpathparser.py
tuia/remoteprocessing.py
tuia/testcase.py
tuia/uiacontrols.py
tuia/util.py
tuia/webcontrols.py
tuia/wincontrols.py
tuia/wintypes.py
qtaf-5.6.11.dist-info/METADATA
qtaf-5.6.11.dist-info/WHEEL
qtaf-5.6.11.dist-info/entry_points.txt
qtaf-5.6.11.dist-info/top_level.txt
qtaf-5.6.11.dist-info/RECORD
