Metadata-Version: 2.4
Name: qtaf
Version: 5.6.11
Summary: Basic test automation framework for QTA
Home-page: https://github.com/Tencent/QTAF
Author: Tencent
License: Copyright(c)2010-2018 Tencent All Rights Reserved. 
Project-URL: TestBase Documentation, https://qta-testbase.readthedocs.io/zh/latest/
Project-URL: TUIA Documentation, https://qta-tuia.readthedocs.io/zh/latest/
Classifier: Programming Language :: Python :: 2.7
Classifier: Operating System :: OS Independent
License-File: LICENSE.TXT
Requires-Dist: six>=1.11.0
Requires-Dist: ply==3.11
Requires-Dist: setuptools
Dynamic: author
Dynamic: classifier
Dynamic: description
Dynamic: description-content-type
Dynamic: home-page
Dynamic: license
Dynamic: license-file
Dynamic: project-url
Dynamic: requires-dist
Dynamic: summary
